{
    "publisher": "SUSE",
    "label": "openSUSE Leap 42.2",
    "displayName": "openSUSE Leap 42.2",
    "cloudEnvironments": [
        "PublicAzure",
        "Blackforest",
        "Mooncake",
        "Fairfax"
    ],
    "mediaReferences": {
        "PublicAzure": {
            "mediaName": "b4590d9e3ed742e4a1d46e5424aa335e__suse-opensuse-leap-42-2-v20170320"
        },
        "Blackforest": {
            "mediaName": "70590eaf9f5e4a7793fcf336be781bb2__suse-opensuse-leap-42-2-v20170320"
        },
        "Mooncake": {
            "mediaName": "250d269906be4694a10aee49a3385f2d__suse-opensuse-leap-42.2-v20170124"
        },
        "Fairfax": {
            "mediaName": "e662d5b5455d4b99afca2432016edc39__suse-opensuse-leap-42.2-v20170124"
        }
    },
    "imageReference": {
      "publisher": "SUSE",
      "offer": "openSUSE-Leap",
      "sku": "42.2"
    },
    "OS": "Linux",
    "description": "Stable, innovative, and fun! A year's worth of continuous improvement in tools and procedures, and countless hours developing, packaging, and testing have produced a stable release providing the best of Free and Open Source software with our special green touch. Customization of these virtual machine (VM) images can be done at <a href='http://susestudio.com' target='_blank'>SUSE Studio</a> or in the <a href='https://build.opensuse.org/project/subprojects/Cloud:Images' target='_blank'>openSUSE Build Service</a>",
    "iconPath": "Icons/openSUSE",
    "categories": [
        "virtualMachine",
        "microsoftServer",
        "azure",
        "linux",
        "appInfra",
        "azureCertified",
        "virtualMachineRecommended"
    ],
    "recommendedSizes": [
        "Standard_DS1_v2",
        "Standard_DS2_v2",
        "Standard_DS11_v2",
        "Standard_DS1",
        "Standard_DS2",
        "Standard_DS11",
        "Standard_D1_v2",
        "Standard_D1",
        "Small"
    ],
    "linksForEnvironments": [
        {
            "label": "Learn more",
            "uri": {
                "Default": "http://opensuse.org/"
            }
        },
        {
            "label": "Documentation",
            "uri": {
                "Default": "http://opensuse.org/Portal:Documentation"
            }
        },
        {
            "label": "Pricing details",
            "uri": {
                "Default": "http://azure.microsoft.com/en-us/pricing/details/virtual-machines/#linux"
            }
        }
    ],
    "eula": "https://en.opensuse.org/openSUSE:License",
    "privacy": null,
    "screenshot": "Screenshots/opensuse.png"
}
